api_to_yaml/__init__.py
api_to_yaml/cli.py
api_to_yaml/clients/__init__.py
api_to_yaml/clients/ghe.py
api_to_yaml/clients/mod.py
api_to_yaml/create/__init__.py
api_to_yaml/create/aws_appmesh.py
api_to_yaml/create/aws_elbv2_create.py
api_to_yaml/create/aws_secretsmanager.py
api_to_yaml/create/mod.py
api_to_yaml/delete/mod.py
api_to_yaml/diff/__init__.py
api_to_yaml/diff/mod.py
api_to_yaml/export/mod.py
api_to_yaml/layout/__init__.py
api_to_yaml/layout/mod.py
api_to_yaml/operators/mod.py
api_to_yaml/plugins/mod.py
api_to_yaml/plugins/wea_notify.py
api_to_yaml/preprocess/__init__.py
api_to_yaml/preprocess/mod.py
api_to_yaml/preprocess/verify.py
api_to_yaml/read/mod.py
api_to_yaml/update/__init__.py
api_to_yaml/update/aws_iam_update.py
api_to_yaml/update/aws_sg_update.py
api_to_yaml/update/ghe_update.py
api_to_yaml/update/mod.py
api_to_yaml/utils/__init__.py
api_to_yaml/utils/dump.py
api_to_yaml/validate/mod.py
cinta-1.0.22.dist-info/METADATA
cinta-1.0.22.dist-info/WHEEL
cinta-1.0.22.dist-info/licenses/LICENSE
cinta-1.0.22.dist-info/RECORD
